simpgraph/__init__.py
simpgraph/simpgraph.py
simpgraph-1.0.0.dist-info/LICENSE
simpgraph-1.0.0.dist-info/METADATA
simpgraph-1.0.0.dist-info/WHEEL
simpgraph-1.0.0.dist-info/RECORD
