Metadata-Version: 2.1
Name: simpgraph
Version: 1.0.0
Summary: Simple and minimal Python module for unordered graphs
Home-page: https://github.com/toda-lab/simpgraph
License: MIT
Keywords: mathematics,graph
Author: Takahisa Toda
Author-email: toda@disc.lab.uec.ac.jp
Requires-Python: >=3.8,<4.0
Classifier: Development Status :: 3 - Alpha
Classifier: Intended Audience :: Science/Research
Classifier: License :: OSI Approved :: MIT License
Classifier: Operating System :: OS Independent
Classifier: Programming Language :: Python
Classifier: Programming Language :: Python :: 3
Classifier: Programming Language :: Python :: 3.8
Classifier: Programming Language :: Python :: 3.9
Classifier: Programming Language :: Python :: 3.10
Classifier: Programming Language :: Python :: 3.11
Classifier: Programming Language :: Python :: 3 :: Only
Classifier: Topic :: Scientific/Engineering :: Mathematics
Provides-Extra: docs
Provides-Extra: test
Requires-Dist: Sphinx (>=7.1.2,<8.0.0) ; extra == "docs"
Requires-Dist: graphviz (>=0.20.3,<0.21.0)
Requires-Dist: pallets-sphinx-themes (>=2.1.1,<3.0.0) ; extra == "docs"
Requires-Dist: pytest (>=8.1.1,<9.0.0) ; extra == "test"
Requires-Dist: sphinx-removed-in (>=0.2.1,<0.3.0) ; extra == "docs"
Requires-Dist: sphinxcontrib-trio (>=1.1.2,<2.0.0) ; extra == "docs"
Project-URL: Repository, https://github.com/toda-lab/simpgraph
